hack4u/__init__.py
hack4u/cursos.py
hack4u/utils.py
hack4U_Grx-0.1.1.dist-info/METADATA
hack4U_Grx-0.1.1.dist-info/WHEEL
hack4U_Grx-0.1.1.dist-info/top_level.txt
hack4U_Grx-0.1.1.dist-info/RECORD
