Metadata-Version: 2.1
Name: hack4U_Grx
Version: 0.1.1
Summary: Biblioteca para consultar cursos de hack4u
Home-page: https://hack4u.io
Author: David Martínez
